rust_template/__init__.py
rust_template/binaries/linux-arm64-gnu/rust_template
rust_template/binaries/linux-x64-gnu/rust_template
rust_template/binaries/macos-arm64/rust_template
rust_template/binaries/macos-x64/rust_template
rust_template/binaries/windows-arm64/rust_template.exe
rust_template/binaries/windows-x64/rust_template.exe
rust_template-0.1.31.dist-info/WHEEL
rust_template-0.1.31.dist-info/entry_points.txt
rust_template-0.1.31.dist-info/METADATA
rust_template-0.1.31.dist-info/RECORD
