Metadata-Version: 2.3
Name: rust-template
Version: 0.1.31
Summary: A production-ready Rust project template to bootstrap new projects fast. It includes a clean Cargo layout, Docker, and a complete CI/CD suite.
Keywords: cli,ai,coding-assistant,telemetry,claude,codex,gemini,usage-tracker,analytics
Author: Wei Lee
Author-email: Wei Lee <mai@mai0313.com>
License: MIT
Classifier: Development Status :: 4 - Beta
Classifier: Intended Audience :: Developers
Classifier: License :: OSI Approved :: MIT License
Classifier: Programming Language :: Python :: 3
Classifier: Programming Language :: Python :: 3.8
Classifier: Programming Language :: Python :: 3.9
Classifier: Programming Language :: Python :: 3.10
Classifier: Programming Language :: Python :: 3.11
Classifier: Programming Language :: Python :: 3.12
Classifier: Programming Language :: Python :: 3.13
Classifier: Operating System :: OS Independent
Classifier: Topic :: Software Development :: Libraries :: Python Modules
Requires-Python: >=3.8
Project-URL: Bug Tracker, https://github.com/Mai0313/rust_template/issues
Project-URL: Homepage, https://github.com/Mai0313/rust_template
Project-URL: Repository, https://github.com/Mai0313/rust_template
